vlt/__init__.py
vlt/config.py
vlt/constants.py
vlt/json_source.py
vlt/vault_source.py
vault_pydantic_simple-0.5.0.dist-info/METADATA
vault_pydantic_simple-0.5.0.dist-info/WHEEL
vault_pydantic_simple-0.5.0.dist-info/top_level.txt
vault_pydantic_simple-0.5.0.dist-info/RECORD
